odoo/addons/stock_lot_image/README.rst
odoo/addons/stock_lot_image/__init__.py
odoo/addons/stock_lot_image/__manifest__.py
odoo/addons/stock_lot_image/i18n/es.po
odoo/addons/stock_lot_image/i18n/it.po
odoo/addons/stock_lot_image/i18n/stock_lot_image.pot
odoo/addons/stock_lot_image/models/__init__.py
odoo/addons/stock_lot_image/models/stock_lot.py
odoo/addons/stock_lot_image/models/stock_lot_image.py
odoo/addons/stock_lot_image/readme/CONTRIBUTORS.md
odoo/addons/stock_lot_image/readme/DESCRIPTION.md
odoo/addons/stock_lot_image/readme/USAGE.md
odoo/addons/stock_lot_image/security/ir.model.access.csv
odoo/addons/stock_lot_image/static/description/icon.png
odoo/addons/stock_lot_image/static/description/index.html
odoo/addons/stock_lot_image/static/src/scss/stock_lot_image_backend.scss
odoo/addons/stock_lot_image/views/stock_lot_image_views.xml
odoo/addons/stock_lot_image/views/stock_lot_views.xml
odoo_addon_stock_lot_image-18.0.1.0.0.4.dist-info/METADATA
odoo_addon_stock_lot_image-18.0.1.0.0.4.dist-info/WHEEL
odoo_addon_stock_lot_image-18.0.1.0.0.4.dist-info/top_level.txt
odoo_addon_stock_lot_image-18.0.1.0.0.4.dist-info/RECORD
